lsf_stats/__init__.py
lsf_stats/cli.py
lsf_stats/gather.py
lsf_stats/summarize.py
lsf_stats-0.3.0.dist-info/entry_points.txt
lsf_stats-0.3.0.dist-info/WHEEL
lsf_stats-0.3.0.dist-info/METADATA
lsf_stats-0.3.0.dist-info/RECORD
