Metadata-Version: 2.1
Name: lsf-stats
Version: 0.3.0
Summary: Summarize LSF job properties by parsing log files.
Home-page: https://github.com/kpj/lsf_stats
License: MIT
Author: kpj
Author-email: kim.philipp.jablonski@gmail.com
Requires-Python: >=3.8.0,<4.0.0
Classifier: License :: OSI Approved :: MIT License
Classifier: Programming Language :: Python :: 3
Classifier: Programming Language :: Python :: 3.8
Classifier: Programming Language :: Python :: 3.9
Requires-Dist: click (>=8.0.1,<9.0.0)
Requires-Dist: humanize (>=3.9.0,<4.0.0)
Requires-Dist: ipython (>=7.24.1,<8.0.0)
Requires-Dist: matplotlib (>=3.4.2,<4.0.0)
Requires-Dist: pandas (>=1.2.4,<2.0.0)
Requires-Dist: pyskim (==0.1.3)
Requires-Dist: seaborn (>=0.11.1,<0.12.0)
Requires-Dist: tqdm (>=4.61.1,<5.0.0)
Project-URL: Repository, https://github.com/kpj/lsf_stats
